Workbook

Sheet Dashboard
B2: Retail Sales Performance Dashboard
B3: Source: SampleSuperstore.csv (cleaned) — Sales, Profit & Category performance overview
B5: Total Sales | D5: Total Profit | F5: Total Orders | H5: Overall Profit Margin
B6: =SUM(RawData_Cleaned!N:N) -> 387904.92 | D6: =SUM(RawData_Cleaned!Q:Q) -> 16146.15 | F6: =SUMPRODUCT((RawData_Cleaned!A2:A376<>"")/COUNTIF(RawData_Cleaned!A2:A376,RawData_Cleaned!A2:A376&"")) -> 260 | H6: =SUM(RawData_Cleaned!Q:Q)/SUM(RawData_Cleaned!N:N) -> 0.041623989
B9: Sales by Category

Sheet RawData_Cleaned
A1: Order ID | B1: Order Date | C1: Ship Date | D1: Ship Mode | E1: Customer ID | F1: Segment | G1: Country | H1: City | I1: State | J1: Region | K1: Product ID | L1: Category | M1: Sub-Category | N1: Sales | O1: Quantity | P1: Discount | Q1: Profit
A2: US-2022-101155 | B2: 2022-11-29 | C2: 2022-12-06 | D2: First Class | E2: CU-10025 | F2: Consumer | G2: United States | H2: Los Angeles | I2: California | J2: West | K2: OFF-PAP-5475 | L2: Office Supplies | M2: Paper | N2: 78.8 | O2: 8 | P2: 0.1 | Q2: 26.61
A3: US-2022-101041 | B3: 2022-01-29 | C3: 2022-01-30 | D3: Standard Class | E3: CU-10222 | F3: Consumer | G3: United States | H3: Springfield | I3: Illinois | J3: Central | K3: TEC-PHO-4114 | L3: Technology | M3: Phones | N3: 3423.42 | O3: 9 | P3: 0.6 | Q3: -704.3
A4: US-2023-101351 | B4: 2022-03-11 | C4: 2022-03-12 | D4: Same Day | E4: CU-10203 | F4: Consumer | G4: United States | H4: Chicago | I4: Illinois | J4: Central | K4: OFF-SUP-2350 | L4: Office Supplies | M4: Supplies | N4: 539.98 | O4: 7 | P4: 0.1 | Q4: 3.6
A5: US-2022-101118 | B5: 2023-03-29 | C5: 2023-04-01 | D5: First Class | E5: CU-10101 | F5: Corporate | G5: United States | H5: Cleveland | I5: Ohio | J5: Central | K5: TEC-MAC-5497 | L5: Technology | M5: Machines | N5: 788.45 | O5: 1 | P5: 0.1 | Q5: 12.98
A6: US-2023-101380 | B6: 2023-04-29 | C6: 2023-05-04 | D6: Standard Class | E6: CU-10123 | F6: Consumer | G6: United States | H6: Chicago | I6: Illinois | J6: Central | K6: TEC-ACC-6813 | L6: Technology | M6: Accessories | N6: 572.88 | O6: 4 | P6: 0.1 | Q6: 134.71
A7: US-2022-101268 | B7: 2023-07-07 | C7: 2023-07-09 | D7: First Class | E7: CU-10294 | F7: Consumer | G7: United States | H7: Spokane | I7: Washington | J7: West | K7: OFF-LAB-9540 | L7: Office Supplies | M7: Labels | N7: 18.2 | O7: 4 | P7: 0 | Q7: 5.98
A8: US-2024-101523 | B8: 2022-10-11 | C8: 2022-10-13 | D8: Standard Class | E8: CU-10089 | F8: Home Office | G8: United States | H8: Worcester | I8: Massachusetts | J8: East | K8: FUR-BOO-9409 | L8: Furniture | M8: Bookcases | N8: 2334.15 | O8: 9 | P8: 0.2 | Q8: -58.93
A9: US-2022-101342 | B9: 2022-03-14 | C9: 2022-03-16 | D9: Standard Class | E9: CU-10188 | F9: Consumer | G9: United States | H9: Tampa | I9: Florida | J9: South | K9: OFF-BIN-3480 | L9: Office Supplies | M9: Binders | N9: 88.96 | O9: 8 | P9: 0.3 | Q9: -11.76
A10: US-2024-101447 | B10: 2023-05-26 | C10: 2023-05-30 | D10: Second Class | E10: CU-10052 | F10: Home Office | G10: United States | H10: Dallas | I10: Texas | J10: Central | K10: FUR-BOO-5990 | L10: Furniture | M10: Bookcases | N10: 539.32 | O10: 2 | P10: 0.15 | Q10: -1.01
A11: US-2024-101016 | B11: 2023-11-07 | C11: 2023-11-11 | D11: Same Day | E11: CU-10102 | F11: Consumer | G11: United States | H11: Jersey City | I11: New Jersey | J11: East | K11: OFF-ART-4770 | L11: Office Supplies | M11: Art | N11: 154.38 | O11: 6 | P11: 0.6 | Q11: -30.99
A12: US-2023-101317 | B12: 2022-07-11 | C12: 2022-07-14 | D12: Standard Class | E12: CU-10250 | F12: Consumer | G12: United States | H12: Springfield | I12: Illinois | J12: Central | K12: OFF-PAP-6766 | L12: Office Supplies | M12: Paper | N12: 201.25 | O12: 7 | P12: 0 | Q12: 75.21
A13: US-2024-101282 | B13: 2023-05-15 | C13: 2023-05-16 | D13: Standard Class | E13: CU-10140 | F13: Consumer | G13: United States | H13: Las Vegas | I13: Nevada | J13: West | K13: OFF-SUP-2753 | L13: Office Supplies | M13: Supplies | N13: 583.1 | O13: 7 | P13: 0 | Q13: 3.71
... A376: US-2023-101262 | B376: 2022-12-23 | C376: 2022-12-24 | D376: Same Day | E376: CU-10001 | F376: Home Office | G376: United States | H376: Boston | I376: Massachusetts | J376: East | K376: OFF-LAB-1527 | L376: Office Supplies | M376: Labels | N376: 42.21 | O376: 3 | P376: 0 | Q376: 15.67
A379: Data cleaning note: started with 390 rows; removed 15 exact duplicate row(s) using Data > Remove Duplicates (all columns); 375 rows remain.
A380: Note: Order ID can legitimately repeat because one order may contain several product line items — duplicates were removed on full-row match, not by forcing one row per Order ID, which would delete genuine sales lines.
A382: Conditional formatting: rows highlighted in red have Discount > 20% AND Profit < 0 (high-discount loss-making orders).

Sheet Region_Summary
A1: Sales & Profit by Region
A2: (Pivot-style summary — built with SUMIFS/COUNTIFS so it recalculates automatically; can also be reproduced as a native Excel PivotTable via Insert > PivotTable on RawData_Cleaned)
A4: Region | B4: Total Sales | C4: Total Profit | D4: Order Count | E4: Profit Margin %
A5: Central | B5: =SUMIFS(RawData_Cleaned!N:N,RawData_Cleaned!J:J,A5) -> 84888.59 | C5: =SUMIFS(RawData_Cleaned!Q:Q,RawData_Cleaned!J:J,A5) -> 2782.65 | D5: =COUNTIFS(RawData_Cleaned!J:J,A5) -> 98 | E5: =C5/B5 -> 0.032780024
A6: East | B6: =SUMIFS(RawData_Cleaned!N:N,RawData_Cleaned!J:J,A6) -> 129349.9 | C6: =SUMIFS(RawData_Cleaned!Q:Q,RawData_Cleaned!J:J,A6) -> 6944.33 | D6: =COUNTIFS(RawData_Cleaned!J:J,A6) -> 93 | E6: =C6/B6 -> 0.053686396
A7: South | B7: =SUMIFS(RawData_Cleaned!N:N,RawData_Cleaned!J:J,A7) -> 72473.36 | C7: =SUMIFS(RawData_Cleaned!Q:Q,RawData_Cleaned!J:J,A7) -> -604.81 | D7: =COUNTIFS(RawData_Cleaned!J:J,A7) -> 110 | E7: =C7/B7 -> -0.0083452734
A8: West | B8: =SUMIFS(RawData_Cleaned!N:N,RawData_Cleaned!J:J,A8) -> 101193.07 | C8: =SUMIFS(RawData_Cleaned!Q:Q,RawData_Cleaned!J:J,A8) -> 7023.98 | D8: =COUNTIFS(RawData_Cleaned!J:J,A8) -> 74 | E8: =C8/B8 -> 0.06941167
A9: Total | B9: =SUM(B5:B8) -> 387904.92 | C9: =SUM(C5:C8) -> 16146.15 | D9: =SUM(D5:D8) -> 375
A11: Highest-profit region: | B11: =INDEX(A5:A8,MATCH(MAX(C5:C8),C5:C8,0)) -> West

Sheet Category_SubCategory
A1: Sales & Profit by Category / Sub-Category
A3: Category | B3: Total Sales | C3: Total Profit | D3: Order Count
A4: Furniture | B4: =SUMIFS(RawData_Cleaned!N:N,RawData_Cleaned!L:L,A4) -> 91154.9 | C4: =SUMIFS(RawData_Cleaned!Q:Q,RawData_Cleaned!L:L,A4) -> -8401.64 | D4: =COUNTIFS(RawData_Cleaned!L:L,A4) -> 94
A5: Office Supplies | B5: =SUMIFS(RawData_Cleaned!N:N,RawData_Cleaned!L:L,A5) -> 48004.94 | C5: =SUMIFS(RawData_Cleaned!Q:Q,RawData_Cleaned!L:L,A5) -> 4374.11 | D5: =COUNTIFS(RawData_Cleaned!L:L,A5) -> 207
A6: Technology | B6: =SUMIFS(RawData_Cleaned!N:N,RawData_Cleaned!L:L,A6) -> 248745.08 | C6: =SUMIFS(RawData_Cleaned!Q:Q,RawData_Cleaned!L:L,A6) -> 20173.68 | D6: =COUNTIFS(RawData_Cleaned!L:L,A6) -> 74
A9: Sub-Category | B9: Total Sales | C9: Total Profit
A10: Accessories | B10: =SUMIFS(RawData_Cleaned!N:N,RawData_Cleaned!M:M,A10) -> 6066 | C10: =SUMIFS(RawData_Cleaned!Q:Q,RawData_Cleaned!M:M,A10) -> 900.81
A11: Appliances | B11: =SUMIFS(RawData_Cleaned!N:N,RawData_Cleaned!M:M,A11) -> 17727.74 | C11: =SUMIFS(RawData_Cleaned!Q:Q,RawData_Cleaned!M:M,A11) -> 1700.84
A12: Art | B12: =SUMIFS(RawData_Cleaned!N:N,RawData_Cleaned!M:M,A12) -> 1874.72 | C12: =SUMIFS(RawData_Cleaned!Q:Q,RawData_Cleaned!M:M,A12) -> 357.34
A13: Binders | B13: =SUMIFS(RawData_Cleaned!N:N,RawData_Cleaned!M:M,A13) -> 2405.16 | C13: =SUMIFS(RawData_Cleaned!Q:Q,RawData_Cleaned!M:M,A13) -> -453.78
A14: Bookcases | B14: =SUMIFS(RawData_Cleaned!N:N,RawData_Cleaned!M:M,A14) -> 23226.9 | C14: =SUMIFS(RawData_Cleaned!Q:Q,RawData_Cleaned!M:M,A14) -> -2433.45
A15: Chairs | B15: =SUMIFS(RawData_Cleaned!N:N,RawData_Cleaned!M:M,A15) -> 28440.49 | C15: =SUMIFS(RawData_Cleaned!Q:Q,RawData_Cleaned!M:M,A15) -> -877.21
A16: Copiers | B16: =SUMIFS(RawData_Cleaned!N:N,RawData_Cleaned!M:M,A16) -> 76194.61 | C16: =SUMIFS(RawData_Cleaned!Q:Q,RawData_Cleaned!M:M,A16) -> 18908.82
A17: Envelopes | B17: =SUMIFS(RawData_Cleaned!N:N,RawData_Cleaned!M:M,A17) -> 2244.74 | C17: =SUMIFS(RawData_Cleaned!Q:Q,RawData_Cleaned!M:M,A17) -> 612.34
A18: Fasteners | B18: =SUMIFS(RawData_Cleaned!N:N,RawData_Cleaned!M:M,A18) -> 1363.23 | C18: =SUMIFS(RawData_Cleaned!Q:Q,RawData_Cleaned!M:M,A18) -> 306.74
A19: Furnishings | B19: =SUMIFS(RawData_Cleaned!N:N,RawData_Cleaned!M:M,A19) -> 10504.73 | C19: =SUMIFS(RawData_Cleaned!Q:Q,RawData_Cleaned!M:M,A19) -> 1733.88
A20: Labels | B20: =SUMIFS(RawData_Cleaned!N:N,RawData_Cleaned!M:M,A20) -> 1183.94 | C20: =SUMIFS(RawData_Cleaned!Q:Q,RawData_Cleaned!M:M,A20) -> 343.82
A21: Machines | B21: =SUMIFS(RawData_Cleaned!N:N,RawData_Cleaned!M:M,A21) -> 111788.44 | C21: =SUMIFS(RawData_Cleaned!Q:Q,RawData_Cleaned!M:M,A21) -> -3922.22
... A26: Tables | B26: =SUMIFS(RawData_Cleaned!N:N,RawData_Cleaned!M:M,A26) -> 28982.78 | C26: =SUMIFS(RawData_Cleaned!Q:Q,RawData_Cleaned!M:M,A26) -> -6824.86

Sheet Top5_Profitable_SubCategories
A1: Top 5 Most Profitable Sub-Categories
A2: (Findings recorded as a comment on the 'Sub-Category' header cell below — hover/right-click to view)
A3: Rank | B3: Sub-Category | C3: Total Profit
A4: 1 | B4: =INDEX(Category_SubCategory!$A$10:$A$26,MATCH(C4,Category_SubCategory!$C$10:$C$26,0)) -> Copiers | C4: =LARGE(Category_SubCategory!$C$10:$C$26,1) -> 18908.82
A5: 2 | B5: =INDEX(Category_SubCategory!$A$10:$A$26,MATCH(C5,Category_SubCategory!$C$10:$C$26,0)) -> Phones | C5: =LARGE(Category_SubCategory!$C$10:$C$26,2) -> 4286.27
A6: 3 | B6: =INDEX(Category_SubCategory!$A$10:$A$26,MATCH(C6,Category_SubCategory!$C$10:$C$26,0)) -> Furnishings | C6: =LARGE(Category_SubCategory!$C$10:$C$26,3) -> 1733.88
A7: 4 | B7: =INDEX(Category_SubCategory!$A$10:$A$26,MATCH(C7,Category_SubCategory!$C$10:$C$26,0)) -> Appliances | C7: =LARGE(Category_SubCategory!$C$10:$C$26,4) -> 1700.84
A8: 5 | B8: =INDEX(Category_SubCategory!$A$10:$A$26,MATCH(C8,Category_SubCategory!$C$10:$C$26,0)) -> Storage | C8: =LARGE(Category_SubCategory!$C$10:$C$26,5) -> 909.02
