Workbook

Sheet Employees
A1: EmpID | B1: Employee Name | C1: Department | D1: Salary
A2: E001 | B2: Employee 1 | C2: IT | D2: 71277
A3: E002 | B3: Employee 2 | C3: HR | D3: 81140
A4: E003 | B4: Employee 3 | C4: Loans | D4: 56801
A5: E004 | B5: Employee 4 | C5: Operations | D5: 76431
A6: E005 | B6: Employee 5 | C6: Operations | D6: 59686
A7: E006 | B7: Employee 6 | C7: Loans | D7: 63531
A8: E007 | B8: Employee 7 | C8: Loans | D8: 86125
A9: E008 | B9: Employee 8 | C9: Operations | D9: 62443
A10: E009 | B10: Employee 9 | C10: HR | D10: 65849
A11: E010 | B11: Employee 10 | C11: Loans | D11: 74635
A12: E011 | B12: Employee 11 | C12: HR | D12: 77717
A13: E012 | B13: Employee 12 | C13: IT | D13: 74859
... A101: E100 | B101: Employee 100 | C101: Loans | D101: 73508

Sheet Transactions
A1: TxnID | B1: Date | C1: Customer | D1: Department | E1: Revenue | F1: Expense | G1: Profit/Loss
A2: T001 | B2: 46025 | C2: Customer 1 | D2: IT | E2: 43371 | F2: 48231 | G2: =E2-F2 -> -4860
A3: T002 | B3: 46026 | C3: Customer 2 | D3: Operations | E3: 48260 | F3: 29673 | G3: =E3-F3 -> 18587
A4: T003 | B4: 46027 | C4: Customer 3 | D4: HR | E4: 59644 | F4: 40579 | G4: =E4-F4 -> 19065
A5: T004 | B5: 46028 | C5: Customer 4 | D5: HR | E5: 82963 | F5: 62900 | G5: =E5-F5 -> 20063
A6: T005 | B6: 46029 | C6: Customer 5 | D6: Accounts | E6: 86752 | F6: 68259 | G6: =E6-F6 -> 18493
A7: T006 | B7: 46030 | C7: Customer 6 | D7: Accounts | E7: 94843 | F7: 16435 | G7: =E7-F7 -> 78408
A8: T007 | B8: 46031 | C8: Customer 7 | D8: Accounts | E8: 37164 | F8: 37576 | G8: =E8-F8 -> -412
A9: T008 | B9: 46032 | C9: Customer 8 | D9: IT | E9: 57653 | F9: 38067 | G9: =E9-F9 -> 19586
A10: T009 | B10: 46033 | C10: Customer 9 | D10: HR | E10: 72681 | F10: 69278 | G10: =E10-F10 -> 3403
A11: T010 | B11: 46034 | C11: Customer 10 | D11: Loans | E11: 98322 | F11: 27501 | G11: =E11-F11 -> 70821
A12: T011 | B12: 46035 | C12: Customer 11 | D12: Operations | E12: 44337 | F12: 58036 | G12: =E12-F12 -> -13699
A13: T012 | B13: 46036 | C13: Customer 12 | D13: Operations | E13: 20251 | F13: 5456 | G13: =E13-F13 -> 14795
... A101: T100 | B101: 46124 | C101: Customer 100 | D101: Loans | E101: 53249 | F101: 67417 | G101: =E101-F101 -> -14168
D102: Total revenu | E102: =SUM(E2:E101) -> 5617423 | F102: =SUM(F2:F101) -> 3766421

Sheet Summary
A1: Metric | B1: Value
A2: Total Revenue | B2: =SUM(Transactions!E2:E101) -> 5617423
A3: Total Expense | B3: =SUM(Transactions!F2:F101) -> 3766421
A4: Total Profit/Loss | B4: =SUM(Transactions!G2:G101) -> 1851002
A6: Department | B6: Total Salary
A7: Loans | B7: =SUMIF(Employees!C:C,A7,Employees!D:D) -> 1288849
A8: Accounts | B8: =SUMIF(Employees!C:C,A8,Employees!D:D) -> 1078238
A9: Operations | B9: =SUMIF(Employees!C:C,A9,Employees!D:D) -> 1120470
A10: IT | B10: =SUMIF(Employees!C:C,A10,Employees!D:D) -> 941115
A11: HR | B11: =SUMIF(Employees!C:C,A11,Employees!D:D) -> 1426055
A14: Formula total revenue | B14: =SUM(Transactions!E2:E101) -> 5617423
A16: Formula of department of salary sum | B16: =SUMIF(Employees!C:C,A7,Employees!D:D) -> 1288849
